{
  "project_info": {
    "project_number": "508163753120",
    "project_id": "lunisupp",
    "storage_bucket": "lunisupp.appspot.com"
  },
  "client": [
    {
      "client_info": {
        "mobilesdk_app_id": "1:508163753120:android:338b4ef79c608685feb5c5",
        "android_client_info": {
          "package_name": "com.c2gen.lunisupp"
        }
      },
      "oauth_client": [
        {
          "client_id": "508163753120-sqv0rkcjgkmtr4co6kv60kv2tg7oikaf.apps.googleusercontent.com",
          "client_type": 3
        }
      ],
      "api_key": [
        {
          "current_key": "AIzaSyB4jimNsy1HwPDYyaN601MwZabOYI7OaSQ"
        }
      ],
      "services": {
        "appinvite_service": {
          "other_platform_oauth_client": [
            {
              "client_id": "508163753120-sqv0rkcjgkmtr4co6kv60kv2tg7oikaf.apps.googleusercontent.com",
              "client_type": 3
            }
          ]
        }
      }
    }
  ],
  "configuration_version": "1"
}